{
  "student": [
    {
      "rollno": "11",
      "name": "Deepak",
      "studentClass": "V",
      "section": "B",
      "id": "s5"
    },
    {
      "rollno": "1",
      "name": "Manoj",
      "studentClass": "VI",
      "section": "C",
      "id": "s6"
    },
    {
      "rollno": "16",
      "name": "Tharun",
      "studentClass": "VII",
      "section": "A",
      "id": "s7"
    },
    {
      "rollno": "5",
      "name": "Imran",
      "studentClass": "VIII",
      "section": "B",
      "id": "s8"
    },
    {
      "rollno": "12",
      "name": "Arunodhayan",
      "studentClass": "I",
      "section": "C",
      "id": "s9"
    },
    {
      "rollno": "20",
      "name": "Lokesh",
      "studentClass": "X",
      "section": "A",
      "id": "s10"
    },
    {
      "rollno": "8",
      "name": "Naveen",
      "studentClass": "I",
      "section": "B",
      "id": "s11"
    },
    {
      "rollno": "15",
      "name": "Yogesh",
      "studentClass": "II",
      "section": "C",
      "id": "s12"
    },
    {
      "rollno": "2",
      "name": "Gokul",
      "studentClass": "III",
      "section": "A",
      "id": "s13"
    },
    {
      "rollno": "18",
      "name": "Rahul",
      "studentClass": "IV",
      "section": "B",
      "id": "s14"
    },
    {
      "rollno": "6",
      "name": "Charan",
      "studentClass": "V",
      "section": "C",
      "id": "s15"
    },
    {
      "rollno": "13",
      "name": "Karthik",
      "studentClass": "VI",
      "section": "A",
      "id": "s16"
    },
    {
      "rollno": "9",
      "name": "Vignesh",
      "studentClass": "VII",
      "section": "B",
      "id": "s17"
    },
    {
      "rollno": "4",
      "name": "Praveen",
      "studentClass": "VIII",
      "section": "C",
      "id": "s18"
    },
    {
      "rollno": "17",
      "name": "Jagan",
      "studentClass": "IX",
      "section": "A",
      "id": "s19"
    },
    {
      "rollno": "10",
      "name": "Ezhil",
      "studentClass": "X",
      "section": "B",
      "id": "s20"
    },
    {
      "rollno": "23",
      "name": "Tharnish",
      "studentClass": "II",
      "section": "A",
      "id": "DRxMKcyWbJM"
    },
    {
      "rollno": "21",
      "name": "Tharnish",
      "studentClass": "II",
      "section": "A",
      "id": "7eIC8IX-Tuc"
    },
    {
      "rollno": "210",
      "name": "Tharnish",
      "studentClass": "II",
      "section": "A",
      "id": "gqda3Xzldnk"
    },
    {
      "rollno": "2102",
      "name": "Tharnish",
      "studentClass": "II",
      "section": "A",
      "id": "WiVkx1fjJKk"
    },
    {
      "rollno": "21021",
      "name": "Tharnish",
      "studentClass": "II",
      "section": "A",
      "id": "gqLVu5yNngU"
    },
    {
      "rollno": "72",
      "name": "Bda",
      "studentClass": "III",
      "section": "A",
      "id": "EG5D0qCKuQY"
    },
    {
      "rollno": "411",
      "name": "Tharnish",
      "studentClass": "II",
      "section": "A",
      "id": "j_INiS9pu70"
    },
    {
      "rollno": "210212",
      "name": "Tharnish",
      "studentClass": "I",
      "section": "A",
      "id": "k3awfypPSzE"
    },
    {
      "rollno": "4323",
      "name": "Tharnish",
      "studentClass": "I",
      "section": "A",
      "id": "7PBDmoeAOTI"
    }
  ],
  "$schema": "./node_modules/json-server/schema.json"
}